LICENSE
README.md
setup.py
horror_allmovie_scraper/__init__.py
horror_allmovie_scraper.egg-info/PKG-INFO
horror_allmovie_scraper.egg-info/SOURCES.txt
horror_allmovie_scraper.egg-info/dependency_links.txt
horror_allmovie_scraper.egg-info/requires.txt
horror_allmovie_scraper.egg-info/top_level.txt