Metadata-Version: 2.1
Name: horror-allmovie-scraper
Version: 1.0.0
Summary: A python library to search top movies on All Movie.
Home-page: UNKNOWN
Author: DataKund
Author-email: datakund@gmail.com
License: Apache License 2.0
Keywords: allmovie.com allmovie python bot_studio automation movies top-movies movie-rating movie-title
Platform: UNKNOWN
License-File: LICENSE
